setup.py
basic_probabilities/Binomialdistribution.py
basic_probabilities/Gaussiandistribution.py
basic_probabilities/Generaldistribution.py
basic_probabilities/__init__.py
basic_probabilities.egg-info/PKG-INFO
basic_probabilities.egg-info/SOURCES.txt
basic_probabilities.egg-info/dependency_links.txt
basic_probabilities.egg-info/not-zip-safe
basic_probabilities.egg-info/top_level.txt